[
  {
    "id": "269",
    "from_email": "Billingpoint <no-reply@onit.com>",
    "to_email": "Suphattra",
    "subject": "Billing Point secure login code",
    "received_at": "2026-04-10T06:22:37+00:00",
    "otp_code": "756287",
    "virtru_link": null,
    "valid_until": null,
    "expiry_str": "ไม่ระบุ",
    "expiry_minutes": null,
    "expires_at": null,
    "system_name": "Billing Point (Onit)",
    "system_url": "https://billingpoint.onit.com",
    "color": "#7c3aed",
    "parsed_at": "2026-04-10T07:34:53.521137+00:00"
  },
  {
    "id": "268",
    "from_email": "hqimtsc.noreply@nestle.com",
    "to_email": "Rutorn",
    "subject": " OTP Verification Nestlé Invoice Management Tool",
    "received_at": "2026-04-10T03:47:00+00:00",
    "otp_code": "176801",
    "virtru_link": null,
    "valid_until": null,
    "expiry_str": "ไม่ระบุ",
    "expiry_minutes": null,
    "expires_at": null,
    "system_name": "Nestlé Invoice Management",
    "system_url": "https://nestle.com",
    "color": "#c8102e",
    "parsed_at": "2026-04-10T07:34:53.514831+00:00"
  },
  {
    "id": "267",
    "from_email": "donotreply <DoNotReply@qualcomm.com>",
    "to_email": "prabjote@dsb.co.th",
    "subject": "One-time verification code",
    "received_at": "2026-04-10T03:11:16+00:00",
    "otp_code": "442767",
    "virtru_link": null,
    "valid_until": null,
    "expiry_str": "ไม่ระบุ",
    "expiry_minutes": null,
    "expires_at": null,
    "system_name": "Qualcomm (Okta)",
    "system_url": "https://account.qualcomm.com",
    "color": "#3253DC",
    "parsed_at": "2026-04-10T07:34:53.509252+00:00"
  },
  {
    "id": "266",
    "from_email": "hqimtsc.noreply@nestle.com",
    "to_email": "Rutorn",
    "subject": " OTP Verification Nestlé Invoice Management Tool",
    "received_at": "2026-04-10T02:58:23+00:00",
    "otp_code": "317341",
    "virtru_link": null,
    "valid_until": null,
    "expiry_str": "ไม่ระบุ",
    "expiry_minutes": null,
    "expires_at": null,
    "system_name": "Nestlé Invoice Management",
    "system_url": "https://nestle.com",
    "color": "#c8102e",
    "parsed_at": "2026-04-10T07:34:53.500999+00:00"
  },
  {
    "id": "265",
    "from_email": "Billingpoint <no-reply@onit.com>",
    "to_email": "Suphattra",
    "subject": "Billing Point secure login code",
    "received_at": "2026-04-10T01:33:51+00:00",
    "otp_code": "901428",
    "virtru_link": null,
    "valid_until": null,
    "expiry_str": "ไม่ระบุ",
    "expiry_minutes": null,
    "expires_at": null,
    "system_name": "Billing Point (Onit)",
    "system_url": "https://billingpoint.onit.com",
    "color": "#7c3aed",
    "parsed_at": "2026-04-10T07:34:53.494556+00:00"
  },
  {
    "id": "264",
    "from_email": "Billingpoint <no-reply@onit.com>",
    "to_email": "Suphattra",
    "subject": "Billing Point secure login code",
    "received_at": "2026-04-09T12:54:34+00:00",
    "otp_code": "319990",
    "virtru_link": null,
    "valid_until": null,
    "expiry_str": "ไม่ระบุ",
    "expiry_minutes": null,
    "expires_at": null,
    "system_name": "Billing Point (Onit)",
    "system_url": "https://billingpoint.onit.com",
    "color": "#7c3aed",
    "parsed_at": "2026-04-10T07:34:53.487400+00:00"
  },
  {
    "id": "263",
    "from_email": "Mitratech Support <collaborati-noreply@mitratech.com>",
    "to_email": "Rutorn",
    "subject": "Collaborati - Verification Code",
    "received_at": "2026-04-09T09:24:11+00:00",
    "otp_code": "622433",
    "virtru_link": null,
    "valid_until": null,
    "expiry_str": "10 minutes",
    "expiry_minutes": 10,
    "expires_at": "2026-04-09T09:34:11+00:00",
    "system_name": "Collaborati (Mitratech)",
    "system_url": "https://www.collaborati.net",
    "color": "#002453",
    "parsed_at": "2026-04-10T07:34:53.480068+00:00"
  },
  {
    "id": "262",
    "from_email": "Mitratech Support <collaborati-noreply@mitratech.com>",
    "to_email": "Rutorn",
    "subject": "Collaborati - Verification Code",
    "received_at": "2026-04-09T09:11:53+00:00",
    "otp_code": "298499",
    "virtru_link": null,
    "valid_until": null,
    "expiry_str": "10 minutes",
    "expiry_minutes": 10,
    "expires_at": "2026-04-09T09:21:53+00:00",
    "system_name": "Collaborati (Mitratech)",
    "system_url": "https://www.collaborati.net",
    "color": "#002453",
    "parsed_at": "2026-04-10T07:34:53.472933+00:00"
  },
  {
    "id": "261",
    "from_email": "donotreply <DoNotReply@qualcomm.com>",
    "to_email": "prabjote@dsb.co.th",
    "subject": "One-time verification code",
    "received_at": "2026-04-09T06:23:06+00:00",
    "otp_code": "548818",
    "virtru_link": null,
    "valid_until": null,
    "expiry_str": "ไม่ระบุ",
    "expiry_minutes": null,
    "expires_at": null,
    "system_name": "Qualcomm (Okta)",
    "system_url": "https://account.qualcomm.com",
    "color": "#3253DC",
    "parsed_at": "2026-04-10T07:34:53.465741+00:00"
  },
  {
    "id": "260",
    "from_email": "donotreply <DoNotReply@qualcomm.com>",
    "to_email": "prabjote@dsb.co.th",
    "subject": "One-time verification code",
    "received_at": "2026-04-08T07:29:52+00:00",
    "otp_code": "184332",
    "virtru_link": null,
    "valid_until": null,
    "expiry_str": "ไม่ระบุ",
    "expiry_minutes": null,
    "expires_at": null,
    "system_name": "Qualcomm (Okta)",
    "system_url": "https://account.qualcomm.com",
    "color": "#3253DC",
    "parsed_at": "2026-04-10T07:34:53.458523+00:00"
  },
  {
    "id": "259",
    "from_email": "Billingpoint <no-reply@onit.com>",
    "to_email": "Suphattra",
    "subject": "Billing Point secure login code",
    "received_at": "2026-04-08T07:04:05+00:00",
    "otp_code": "256932",
    "virtru_link": null,
    "valid_until": null,
    "expiry_str": "ไม่ระบุ",
    "expiry_minutes": null,
    "expires_at": null,
    "system_name": "Billing Point (Onit)",
    "system_url": "https://billingpoint.onit.com",
    "color": "#7c3aed",
    "parsed_at": "2026-04-10T07:34:53.451997+00:00"
  },
  {
    "id": "258",
    "from_email": "hqimtsc.noreply@nestle.com",
    "to_email": "Rutorn",
    "subject": " OTP Verification Nestlé Invoice Management Tool",
    "received_at": "2026-04-08T03:56:32+00:00",
    "otp_code": "969028",
    "virtru_link": null,
    "valid_until": null,
    "expiry_str": "ไม่ระบุ",
    "expiry_minutes": null,
    "expires_at": null,
    "system_name": "Nestlé Invoice Management",
    "system_url": "https://nestle.com",
    "color": "#c8102e",
    "parsed_at": "2026-04-10T07:34:53.444931+00:00"
  },
  {
    "id": "257",
    "from_email": "donotreply <DoNotReply@qualcomm.com>",
    "to_email": "prabjote@dsb.co.th",
    "subject": "One-time verification code",
    "received_at": "2026-04-08T01:21:53+00:00",
    "otp_code": "923813",
    "virtru_link": null,
    "valid_until": null,
    "expiry_str": "ไม่ระบุ",
    "expiry_minutes": null,
    "expires_at": null,
    "system_name": "Qualcomm (Okta)",
    "system_url": "https://account.qualcomm.com",
    "color": "#3253DC",
    "parsed_at": "2026-04-10T07:34:53.439375+00:00"
  },
  {
    "id": "256",
    "from_email": "west.onepass@thomsonreuters.com",
    "to_email": "Rutorn",
    "subject": "OnePass Security Code",
    "received_at": "2026-04-07T09:31:17+00:00",
    "otp_code": "161252",
    "virtru_link": null,
    "valid_until": null,
    "expiry_str": "15 minutes",
    "expiry_minutes": 15,
    "expires_at": "2026-04-07T09:46:17+00:00",
    "system_name": "OnePass (Thomson Reuters)",
    "system_url": "https://onepass.thomsonreuters.com",
    "color": "#DC2626",
    "parsed_at": "2026-04-10T07:34:53.432074+00:00"
  },
  {
    "id": "255",
    "from_email": "Billingpoint <no-reply@onit.com>",
    "to_email": "Suphattra",
    "subject": "Billing Point secure login code",
    "received_at": "2026-04-07T06:22:44+00:00",
    "otp_code": "752997",
    "virtru_link": null,
    "valid_until": null,
    "expiry_str": "ไม่ระบุ",
    "expiry_minutes": null,
    "expires_at": null,
    "system_name": "Billing Point (Onit)",
    "system_url": "https://billingpoint.onit.com",
    "color": "#7c3aed",
    "parsed_at": "2026-04-10T07:34:53.425867+00:00"
  },
  {
    "id": "254",
    "from_email": "donotreply <DoNotReply@qualcomm.com>",
    "to_email": "prabjote@dsb.co.th",
    "subject": "One-time verification code",
    "received_at": "2026-04-07T04:33:50+00:00",
    "otp_code": "624195",
    "virtru_link": null,
    "valid_until": null,
    "expiry_str": "ไม่ระบุ",
    "expiry_minutes": null,
    "expires_at": null,
    "system_name": "Qualcomm (Okta)",
    "system_url": "https://account.qualcomm.com",
    "color": "#3253DC",
    "parsed_at": "2026-04-10T07:34:53.418834+00:00"
  },
  {
    "id": "253",
    "from_email": "donotreply <DoNotReply@qualcomm.com>",
    "to_email": "prabjote@dsb.co.th",
    "subject": "One-time verification code",
    "received_at": "2026-04-07T00:52:36+00:00",
    "otp_code": "598904",
    "virtru_link": null,
    "valid_until": null,
    "expiry_str": "ไม่ระบุ",
    "expiry_minutes": null,
    "expires_at": null,
    "system_name": "Qualcomm (Okta)",
    "system_url": "https://account.qualcomm.com",
    "color": "#3253DC",
    "parsed_at": "2026-04-10T07:34:53.411737+00:00"
  },
  {
    "id": "252",
    "from_email": "donotreply <DoNotReply@qualcomm.com>",
    "to_email": "prabjote@dsb.co.th",
    "subject": "One-time verification code",
    "received_at": "2026-04-07T00:50:57+00:00",
    "otp_code": "828242",
    "virtru_link": null,
    "valid_until": null,
    "expiry_str": "ไม่ระบุ",
    "expiry_minutes": null,
    "expires_at": null,
    "system_name": "Qualcomm (Okta)",
    "system_url": "https://account.qualcomm.com",
    "color": "#3253DC",
    "parsed_at": "2026-04-10T07:34:53.404717+00:00"
  },
  {
    "id": "251",
    "from_email": "donotreply <DoNotReply@qualcomm.com>",
    "to_email": "prabjote@dsb.co.th",
    "subject": "One-time verification code",
    "received_at": "2026-04-07T00:48:50+00:00",
    "otp_code": "050290",
    "virtru_link": null,
    "valid_until": null,
    "expiry_str": "ไม่ระบุ",
    "expiry_minutes": null,
    "expires_at": null,
    "system_name": "Qualcomm (Okta)",
    "system_url": "https://account.qualcomm.com",
    "color": "#3253DC",
    "parsed_at": "2026-04-10T07:34:53.397519+00:00"
  },
  {
    "id": "250",
    "from_email": "donotreply <DoNotReply@qualcomm.com>",
    "to_email": "prabjote@dsb.co.th",
    "subject": "One-time verification code",
    "received_at": "2026-04-07T00:46:35+00:00",
    "otp_code": "716143",
    "virtru_link": null,
    "valid_until": null,
    "expiry_str": "ไม่ระบุ",
    "expiry_minutes": null,
    "expires_at": null,
    "system_name": "Qualcomm (Okta)",
    "system_url": "https://account.qualcomm.com",
    "color": "#3253DC",
    "parsed_at": "2026-04-10T07:34:53.390569+00:00"
  },
  {
    "id": "249",
    "from_email": "hqimtsc.noreply@nestle.com",
    "to_email": "Chakrapat",
    "subject": " OTP Verification Nestlé Invoice Management Tool",
    "received_at": "2026-04-07T00:11:31+00:00",
    "otp_code": "613311",
    "virtru_link": null,
    "valid_until": null,
    "expiry_str": "ไม่ระบุ",
    "expiry_minutes": null,
    "expires_at": null,
    "system_name": "Nestlé Invoice Management",
    "system_url": "https://nestle.com",
    "color": "#c8102e",
    "parsed_at": "2026-04-10T07:34:53.383806+00:00"
  },
  {
    "id": "248",
    "from_email": "Billingpoint <no-reply@onit.com>",
    "to_email": "Suphattra",
    "subject": "Billing Point secure login code",
    "received_at": "2026-04-03T10:45:38+00:00",
    "otp_code": "249538",
    "virtru_link": null,
    "valid_until": null,
    "expiry_str": "ไม่ระบุ",
    "expiry_minutes": null,
    "expires_at": null,
    "system_name": "Billing Point (Onit)",
    "system_url": "https://billingpoint.onit.com",
    "color": "#7c3aed",
    "parsed_at": "2026-04-10T07:34:53.377591+00:00"
  },
  {
    "id": "247",
    "from_email": "hqimtsc.noreply@nestle.com",
    "to_email": "Chakrapat",
    "subject": " OTP Verification Nestlé Invoice Management Tool",
    "received_at": "2026-04-03T10:23:52+00:00",
    "otp_code": "641926",
    "virtru_link": null,
    "valid_until": null,
    "expiry_str": "ไม่ระบุ",
    "expiry_minutes": null,
    "expires_at": null,
    "system_name": "Nestlé Invoice Management",
    "system_url": "https://nestle.com",
    "color": "#c8102e",
    "parsed_at": "2026-04-10T07:34:53.370318+00:00"
  },
  {
    "id": "246",
    "from_email": "Billingpoint <no-reply@onit.com>",
    "to_email": "Suphattra",
    "subject": "Billing Point secure login code",
    "received_at": "2026-04-03T09:07:01+00:00",
    "otp_code": "565356",
    "virtru_link": null,
    "valid_until": null,
    "expiry_str": "ไม่ระบุ",
    "expiry_minutes": null,
    "expires_at": null,
    "system_name": "Billing Point (Onit)",
    "system_url": "https://billingpoint.onit.com",
    "color": "#7c3aed",
    "parsed_at": "2026-04-10T07:34:53.364023+00:00"
  },
  {
    "id": "245",
    "from_email": "Billingpoint <no-reply@onit.com>",
    "to_email": "Suphattra",
    "subject": "Billing Point secure login code",
    "received_at": "2026-04-03T08:59:16+00:00",
    "otp_code": "577934",
    "virtru_link": null,
    "valid_until": null,
    "expiry_str": "ไม่ระบุ",
    "expiry_minutes": null,
    "expires_at": null,
    "system_name": "Billing Point (Onit)",
    "system_url": "https://billingpoint.onit.com",
    "color": "#7c3aed",
    "parsed_at": "2026-04-10T07:34:53.356806+00:00"
  },
  {
    "id": "244",
    "from_email": "Mitratech Support <collaborati-noreply@mitratech.com>",
    "to_email": "Rutorn",
    "subject": "Collaborati - Verification Code",
    "received_at": "2026-04-03T08:23:15+00:00",
    "otp_code": "278204",
    "virtru_link": null,
    "valid_until": null,
    "expiry_str": "10 minutes",
    "expiry_minutes": 10,
    "expires_at": "2026-04-03T08:33:15+00:00",
    "system_name": "Collaborati (Mitratech)",
    "system_url": "https://www.collaborati.net",
    "color": "#002453",
    "parsed_at": "2026-04-10T07:34:53.347924+00:00"
  },
  {
    "id": "243",
    "from_email": "Mitratech Support <collaborati-noreply@mitratech.com>",
    "to_email": "Rutorn",
    "subject": "Collaborati - Verification Code",
    "received_at": "2026-04-03T07:47:30+00:00",
    "otp_code": "590215",
    "virtru_link": null,
    "valid_until": null,
    "expiry_str": "10 minutes",
    "expiry_minutes": 10,
    "expires_at": "2026-04-03T07:57:30+00:00",
    "system_name": "Collaborati (Mitratech)",
    "system_url": "https://www.collaborati.net",
    "color": "#002453",
    "parsed_at": "2026-04-10T07:34:53.341039+00:00"
  },
  {
    "id": "242",
    "from_email": "donotreply <DoNotReply@qualcomm.com>",
    "to_email": "prabjote@dsb.co.th",
    "subject": "One-time verification code",
    "received_at": "2026-04-03T06:49:29+00:00",
    "otp_code": "220674",
    "virtru_link": null,
    "valid_until": null,
    "expiry_str": "ไม่ระบุ",
    "expiry_minutes": null,
    "expires_at": null,
    "system_name": "Qualcomm (Okta)",
    "system_url": "https://account.qualcomm.com",
    "color": "#3253DC",
    "parsed_at": "2026-04-10T07:34:53.333805+00:00"
  },
  {
    "id": "241",
    "from_email": "hqimtsc.noreply@nestle.com",
    "to_email": "Chakrapat",
    "subject": " OTP Verification Nestlé Invoice Management Tool",
    "received_at": "2026-04-03T00:17:29+00:00",
    "otp_code": "301209",
    "virtru_link": null,
    "valid_until": null,
    "expiry_str": "ไม่ระบุ",
    "expiry_minutes": null,
    "expires_at": null,
    "system_name": "Nestlé Invoice Management",
    "system_url": "https://nestle.com",
    "color": "#c8102e",
    "parsed_at": "2026-04-10T07:34:53.326642+00:00"
  },
  {
    "id": "240",
    "from_email": "Mitratech Support <collaborati-noreply@mitratech.com>",
    "to_email": "Rutorn",
    "subject": "Collaborati - Verification Code",
    "received_at": "2026-04-02T12:24:45+00:00",
    "otp_code": "431578",
    "virtru_link": null,
    "valid_until": null,
    "expiry_str": "10 minutes",
    "expiry_minutes": 10,
    "expires_at": "2026-04-02T12:34:45+00:00",
    "system_name": "Collaborati (Mitratech)",
    "system_url": "https://www.collaborati.net",
    "color": "#002453",
    "parsed_at": "2026-04-10T07:34:53.320770+00:00"
  },
  {
    "id": "239",
    "from_email": "donotreply <DoNotReply@qualcomm.com>",
    "to_email": "prabjote@dsb.co.th",
    "subject": "One-time verification code",
    "received_at": "2026-04-02T04:53:35+00:00",
    "otp_code": "520253",
    "virtru_link": null,
    "valid_until": null,
    "expiry_str": "ไม่ระบุ",
    "expiry_minutes": null,
    "expires_at": null,
    "system_name": "Qualcomm (Okta)",
    "system_url": "https://account.qualcomm.com",
    "color": "#3253DC",
    "parsed_at": "2026-04-10T07:34:53.313692+00:00"
  },
  {
    "id": "238",
    "from_email": "Mitratech Support <collaborati-noreply@mitratech.com>",
    "to_email": "Rutorn",
    "subject": "Collaborati - Verification Code",
    "received_at": "2026-04-01T11:51:29+00:00",
    "otp_code": "522504",
    "virtru_link": null,
    "valid_until": null,
    "expiry_str": "10 minutes",
    "expiry_minutes": 10,
    "expires_at": "2026-04-01T12:01:29+00:00",
    "system_name": "Collaborati (Mitratech)",
    "system_url": "https://www.collaborati.net",
    "color": "#002453",
    "parsed_at": "2026-04-10T07:34:53.306716+00:00"
  },
  {
    "id": "237",
    "from_email": "hqimtsc.noreply@nestle.com",
    "to_email": "Chakrapat",
    "subject": " OTP Verification Nestlé Invoice Management Tool",
    "received_at": "2026-04-01T07:24:23+00:00",
    "otp_code": "319411",
    "virtru_link": null,
    "valid_until": null,
    "expiry_str": "ไม่ระบุ",
    "expiry_minutes": null,
    "expires_at": null,
    "system_name": "Nestlé Invoice Management",
    "system_url": "https://nestle.com",
    "color": "#c8102e",
    "parsed_at": "2026-04-10T07:34:53.299874+00:00"
  },
  {
    "id": "236",
    "from_email": "hqimtsc.noreply@nestle.com",
    "to_email": "Chakrapat",
    "subject": " OTP Verification Nestlé Invoice Management Tool",
    "received_at": "2026-04-01T07:20:36+00:00",
    "otp_code": "736551",
    "virtru_link": null,
    "valid_until": null,
    "expiry_str": "ไม่ระบุ",
    "expiry_minutes": null,
    "expires_at": null,
    "system_name": "Nestlé Invoice Management",
    "system_url": "https://nestle.com",
    "color": "#c8102e",
    "parsed_at": "2026-04-10T07:34:53.293628+00:00"
  },
  {
    "id": "235",
    "from_email": "Mitratech Support <collaborati-noreply@mitratech.com>",
    "to_email": "Rutorn",
    "subject": "Collaborati - Verification Code",
    "received_at": "2026-04-01T03:07:13+00:00",
    "otp_code": "158244",
    "virtru_link": null,
    "valid_until": null,
    "expiry_str": "10 minutes",
    "expiry_minutes": 10,
    "expires_at": "2026-04-01T03:17:13+00:00",
    "system_name": "Collaborati (Mitratech)",
    "system_url": "https://www.collaborati.net",
    "color": "#002453",
    "parsed_at": "2026-04-10T07:34:53.288081+00:00"
  },
  {
    "id": "234",
    "from_email": "west.onepass@thomsonreuters.com",
    "to_email": "Rutorn",
    "subject": "OnePass Security Code",
    "received_at": "2026-04-01T00:39:46+00:00",
    "otp_code": "391131",
    "virtru_link": null,
    "valid_until": null,
    "expiry_str": "15 minutes",
    "expiry_minutes": 15,
    "expires_at": "2026-04-01T00:54:46+00:00",
    "system_name": "OnePass (Thomson Reuters)",
    "system_url": "https://onepass.thomsonreuters.com",
    "color": "#DC2626",
    "parsed_at": "2026-04-10T07:34:53.280964+00:00"
  },
  {
    "id": "233",
    "from_email": "Billingpoint <no-reply@onit.com>",
    "to_email": "Suphattra",
    "subject": "Billing Point secure login code",
    "received_at": "2026-03-31T11:11:19+00:00",
    "otp_code": "777190",
    "virtru_link": null,
    "valid_until": null,
    "expiry_str": "ไม่ระบุ",
    "expiry_minutes": null,
    "expires_at": null,
    "system_name": "Billing Point (Onit)",
    "system_url": "https://billingpoint.onit.com",
    "color": "#7c3aed",
    "parsed_at": "2026-04-10T07:34:53.274705+00:00"
  },
  {
    "id": "232",
    "from_email": "donotreply <DoNotReply@qualcomm.com>",
    "to_email": "prabjote@dsb.co.th",
    "subject": "One-time verification code",
    "received_at": "2026-03-31T09:33:28+00:00",
    "otp_code": "324380",
    "virtru_link": null,
    "valid_until": null,
    "expiry_str": "ไม่ระบุ",
    "expiry_minutes": null,
    "expires_at": null,
    "system_name": "Qualcomm (Okta)",
    "system_url": "https://account.qualcomm.com",
    "color": "#3253DC",
    "parsed_at": "2026-04-10T07:34:53.266879+00:00"
  },
  {
    "id": "231",
    "from_email": "Billingpoint <no-reply@onit.com>",
    "to_email": "Suphattra",
    "subject": "Billing Point secure login code",
    "received_at": "2026-03-31T04:14:04+00:00",
    "otp_code": "749509",
    "virtru_link": null,
    "valid_until": null,
    "expiry_str": "ไม่ระบุ",
    "expiry_minutes": null,
    "expires_at": null,
    "system_name": "Billing Point (Onit)",
    "system_url": "https://billingpoint.onit.com",
    "color": "#7c3aed",
    "parsed_at": "2026-04-10T07:34:53.260004+00:00"
  },
  {
    "id": "230",
    "from_email": "donotreply <DoNotReply@qualcomm.com>",
    "to_email": "prabjote@dsb.co.th",
    "subject": "One-time verification code",
    "received_at": "2026-03-31T03:32:27+00:00",
    "otp_code": "199080",
    "virtru_link": null,
    "valid_until": null,
    "expiry_str": "ไม่ระบุ",
    "expiry_minutes": null,
    "expires_at": null,
    "system_name": "Qualcomm (Okta)",
    "system_url": "https://account.qualcomm.com",
    "color": "#3253DC",
    "parsed_at": "2026-04-10T07:34:53.253464+00:00"
  },
  {
    "id": "229",
    "from_email": "Billingpoint <no-reply@onit.com>",
    "to_email": "Suphattra",
    "subject": "Billing Point secure login code",
    "received_at": "2026-03-30T05:38:32+00:00",
    "otp_code": "787410",
    "virtru_link": null,
    "valid_until": null,
    "expiry_str": "ไม่ระบุ",
    "expiry_minutes": null,
    "expires_at": null,
    "system_name": "Billing Point (Onit)",
    "system_url": "https://billingpoint.onit.com",
    "color": "#7c3aed",
    "parsed_at": "2026-04-10T07:34:53.245990+00:00"
  },
  {
    "id": "228",
    "from_email": "donotreply <DoNotReply@qualcomm.com>",
    "to_email": "prabjote@dsb.co.th",
    "subject": "One-time verification code",
    "received_at": "2026-03-30T03:12:01+00:00",
    "otp_code": "767138",
    "virtru_link": null,
    "valid_until": null,
    "expiry_str": "ไม่ระบุ",
    "expiry_minutes": null,
    "expires_at": null,
    "system_name": "Qualcomm (Okta)",
    "system_url": "https://account.qualcomm.com",
    "color": "#3253DC",
    "parsed_at": "2026-04-10T07:34:53.238787+00:00"
  },
  {
    "id": "227",
    "from_email": "donotreply <DoNotReply@qualcomm.com>",
    "to_email": "prabjote@dsb.co.th",
    "subject": "One-time verification code",
    "received_at": "2026-03-30T02:36:49+00:00",
    "otp_code": "645595",
    "virtru_link": null,
    "valid_until": null,
    "expiry_str": "ไม่ระบุ",
    "expiry_minutes": null,
    "expires_at": null,
    "system_name": "Qualcomm (Okta)",
    "system_url": "https://account.qualcomm.com",
    "color": "#3253DC",
    "parsed_at": "2026-04-10T07:34:53.231299+00:00"
  },
  {
    "id": "226",
    "from_email": "Billingpoint <no-reply@onit.com>",
    "to_email": "Suphattra",
    "subject": "Billing Point secure login code",
    "received_at": "2026-03-29T12:52:35+00:00",
    "otp_code": "145254",
    "virtru_link": null,
    "valid_until": null,
    "expiry_str": "ไม่ระบุ",
    "expiry_minutes": null,
    "expires_at": null,
    "system_name": "Billing Point (Onit)",
    "system_url": "https://billingpoint.onit.com",
    "color": "#7c3aed",
    "parsed_at": "2026-04-10T07:34:53.223853+00:00"
  },
  {
    "id": "225",
    "from_email": "Mitratech Support <collaborati-noreply@mitratech.com>",
    "to_email": "Rutorn",
    "subject": "Collaborati - Verification Code",
    "received_at": "2026-03-27T08:13:33+00:00",
    "otp_code": "660031",
    "virtru_link": null,
    "valid_until": null,
    "expiry_str": "10 minutes",
    "expiry_minutes": 10,
    "expires_at": "2026-03-27T08:23:33+00:00",
    "system_name": "Collaborati (Mitratech)",
    "system_url": "https://www.collaborati.net",
    "color": "#002453",
    "parsed_at": "2026-04-10T07:34:53.216613+00:00"
  },
  {
    "id": "224",
    "from_email": "Billingpoint <no-reply@onit.com>",
    "to_email": "Suphattra",
    "subject": "Billing Point secure login code",
    "received_at": "2026-03-27T04:51:41+00:00",
    "otp_code": "813493",
    "virtru_link": null,
    "valid_until": null,
    "expiry_str": "ไม่ระบุ",
    "expiry_minutes": null,
    "expires_at": null,
    "system_name": "Billing Point (Onit)",
    "system_url": "https://billingpoint.onit.com",
    "color": "#7c3aed",
    "parsed_at": "2026-04-10T07:34:53.209077+00:00"
  },
  {
    "id": "223",
    "from_email": "donotreply <DoNotReply@qualcomm.com>",
    "to_email": "prabjote@dsb.co.th",
    "subject": "One-time verification code",
    "received_at": "2026-03-27T04:37:32+00:00",
    "otp_code": "293490",
    "virtru_link": null,
    "valid_until": null,
    "expiry_str": "ไม่ระบุ",
    "expiry_minutes": null,
    "expires_at": null,
    "system_name": "Qualcomm (Okta)",
    "system_url": "https://account.qualcomm.com",
    "color": "#3253DC",
    "parsed_at": "2026-04-10T07:34:53.201751+00:00"
  },
  {
    "id": "222",
    "from_email": "Billingpoint <no-reply@onit.com>",
    "to_email": "Suphattra",
    "subject": "Billing Point secure login code",
    "received_at": "2026-03-26T10:41:36+00:00",
    "otp_code": "412197",
    "virtru_link": null,
    "valid_until": null,
    "expiry_str": "ไม่ระบุ",
    "expiry_minutes": null,
    "expires_at": null,
    "system_name": "Billing Point (Onit)",
    "system_url": "https://billingpoint.onit.com",
    "color": "#7c3aed",
    "parsed_at": "2026-04-10T07:34:53.194843+00:00"
  },
  {
    "id": "221",
    "from_email": "donotreply <DoNotReply@qualcomm.com>",
    "to_email": "prabjote@dsb.co.th",
    "subject": "One-time verification code",
    "received_at": "2026-03-26T06:55:03+00:00",
    "otp_code": "329233",
    "virtru_link": null,
    "valid_until": null,
    "expiry_str": "ไม่ระบุ",
    "expiry_minutes": null,
    "expires_at": null,
    "system_name": "Qualcomm (Okta)",
    "system_url": "https://account.qualcomm.com",
    "color": "#3253DC",
    "parsed_at": "2026-04-10T07:34:53.187685+00:00"
  },
  {
    "id": "220",
    "from_email": "CounselLink <no-reply@lexisnexis.com>",
    "to_email": "Rutorn",
    "subject": "CounselLink Multi-factor Authentication Verification Code",
    "received_at": "2026-03-26T03:37:06+00:00",
    "otp_code": "308526",
    "virtru_link": null,
    "valid_until": null,
    "expiry_str": "10 minutes",
    "expiry_minutes": 10,
    "expires_at": "2026-03-26T03:47:06+00:00",
    "system_name": "CounselLink (LexisNexis)",
    "system_url": "https://counsellink.com",
    "color": "#d61f1f",
    "parsed_at": "2026-04-10T07:34:53.180363+00:00"
  },
  {
    "id": "219",
    "from_email": "Billingpoint <no-reply@onit.com>",
    "to_email": "Suphattra",
    "subject": "Billing Point secure login code",
    "received_at": "2026-03-25T10:32:18+00:00",
    "otp_code": "205549",
    "virtru_link": null,
    "valid_until": null,
    "expiry_str": "ไม่ระบุ",
    "expiry_minutes": null,
    "expires_at": null,
    "system_name": "Billing Point (Onit)",
    "system_url": "https://billingpoint.onit.com",
    "color": "#7c3aed",
    "parsed_at": "2026-04-10T07:34:53.172572+00:00"
  },
  {
    "id": "218",
    "from_email": "Mitratech Support <collaborati-noreply@mitratech.com>",
    "to_email": "Rutorn",
    "subject": "Collaborati - Verification Code",
    "received_at": "2026-03-25T10:29:51+00:00",
    "otp_code": "391549",
    "virtru_link": null,
    "valid_until": null,
    "expiry_str": "10 minutes",
    "expiry_minutes": 10,
    "expires_at": "2026-03-25T10:39:51+00:00",
    "system_name": "Collaborati (Mitratech)",
    "system_url": "https://www.collaborati.net",
    "color": "#002453",
    "parsed_at": "2026-04-10T07:34:53.165420+00:00"
  },
  {
    "id": "217",
    "from_email": "Mitratech Support <collaborati-noreply@mitratech.com>",
    "to_email": "Rutorn",
    "subject": "Collaborati - Verification Code",
    "received_at": "2026-03-25T10:28:46+00:00",
    "otp_code": "931174",
    "virtru_link": null,
    "valid_until": null,
    "expiry_str": "10 minutes",
    "expiry_minutes": 10,
    "expires_at": "2026-03-25T10:38:46+00:00",
    "system_name": "Collaborati (Mitratech)",
    "system_url": "https://www.collaborati.net",
    "color": "#002453",
    "parsed_at": "2026-04-10T07:34:53.157933+00:00"
  },
  {
    "id": "216",
    "from_email": "Mitratech Support <collaborati-noreply@mitratech.com>",
    "to_email": "Rutorn",
    "subject": "Collaborati - Verification Code",
    "received_at": "2026-03-25T10:26:49+00:00",
    "otp_code": "781763",
    "virtru_link": null,
    "valid_until": null,
    "expiry_str": "10 minutes",
    "expiry_minutes": 10,
    "expires_at": "2026-03-25T10:36:49+00:00",
    "system_name": "Collaborati (Mitratech)",
    "system_url": "https://www.collaborati.net",
    "color": "#002453",
    "parsed_at": "2026-04-10T07:34:53.150492+00:00"
  },
  {
    "id": "215",
    "from_email": "Billingpoint <no-reply@onit.com>",
    "to_email": "Suphattra",
    "subject": "Billing Point secure login code",
    "received_at": "2026-03-25T10:25:40+00:00",
    "otp_code": "318871",
    "virtru_link": null,
    "valid_until": null,
    "expiry_str": "ไม่ระบุ",
    "expiry_minutes": null,
    "expires_at": null,
    "system_name": "Billing Point (Onit)",
    "system_url": "https://billingpoint.onit.com",
    "color": "#7c3aed",
    "parsed_at": "2026-04-10T07:34:53.142878+00:00"
  },
  {
    "id": "214",
    "from_email": "Mitratech Support <collaborati-noreply@mitratech.com>",
    "to_email": "Rutorn",
    "subject": "Collaborati - Verification Code",
    "received_at": "2026-03-25T10:20:38+00:00",
    "otp_code": "678032",
    "virtru_link": null,
    "valid_until": null,
    "expiry_str": "10 minutes",
    "expiry_minutes": 10,
    "expires_at": "2026-03-25T10:30:38+00:00",
    "system_name": "Collaborati (Mitratech)",
    "system_url": "https://www.collaborati.net",
    "color": "#002453",
    "parsed_at": "2026-04-10T07:34:53.135773+00:00"
  },
  {
    "id": "213",
    "from_email": "Billingpoint <no-reply@onit.com>",
    "to_email": "Suphattra",
    "subject": "Billing Point secure login code",
    "received_at": "2026-03-25T10:16:49+00:00",
    "otp_code": "437244",
    "virtru_link": null,
    "valid_until": null,
    "expiry_str": "ไม่ระบุ",
    "expiry_minutes": null,
    "expires_at": null,
    "system_name": "Billing Point (Onit)",
    "system_url": "https://billingpoint.onit.com",
    "color": "#7c3aed",
    "parsed_at": "2026-04-10T07:34:53.128704+00:00"
  },
  {
    "id": "212",
    "from_email": "Billingpoint <no-reply@onit.com>",
    "to_email": "Suphattra",
    "subject": "Billing Point secure login code",
    "received_at": "2026-03-25T09:02:21+00:00",
    "otp_code": "872687",
    "virtru_link": null,
    "valid_until": null,
    "expiry_str": "ไม่ระบุ",
    "expiry_minutes": null,
    "expires_at": null,
    "system_name": "Billing Point (Onit)",
    "system_url": "https://billingpoint.onit.com",
    "color": "#7c3aed",
    "parsed_at": "2026-04-10T07:34:53.121598+00:00"
  },
  {
    "id": "211",
    "from_email": "donotreply <DoNotReply@qualcomm.com>",
    "to_email": "prabjote@dsb.co.th",
    "subject": "One-time verification code",
    "received_at": "2026-03-25T06:20:50+00:00",
    "otp_code": "169058",
    "virtru_link": null,
    "valid_until": null,
    "expiry_str": "ไม่ระบุ",
    "expiry_minutes": null,
    "expires_at": null,
    "system_name": "Qualcomm (Okta)",
    "system_url": "https://account.qualcomm.com",
    "color": "#3253DC",
    "parsed_at": "2026-04-10T07:34:53.114497+00:00"
  },
  {
    "id": "210",
    "from_email": "Billingpoint <no-reply@onit.com>",
    "to_email": "Suphattra",
    "subject": "Billing Point secure login code",
    "received_at": "2026-03-24T09:27:34+00:00",
    "otp_code": "885327",
    "virtru_link": null,
    "valid_until": null,
    "expiry_str": "ไม่ระบุ",
    "expiry_minutes": null,
    "expires_at": null,
    "system_name": "Billing Point (Onit)",
    "system_url": "https://billingpoint.onit.com",
    "color": "#7c3aed",
    "parsed_at": "2026-04-10T07:34:53.107426+00:00"
  },
  {
    "id": "209",
    "from_email": "Brightflag <invoices@brightflag.com>",
    "to_email": "Suphattra",
    "subject": "Action Needed - Email Verification - Brightflag",
    "received_at": "2026-03-24T07:21:56+00:00",
    "otp_code": "793318",
    "virtru_link": null,
    "valid_until": null,
    "expiry_str": "15 minutes",
    "expiry_minutes": 15,
    "expires_at": "2026-03-24T07:36:56+00:00",
    "system_name": "Brightflag",
    "system_url": "https://brightflag.com",
    "color": "#059669",
    "parsed_at": "2026-04-10T07:34:53.100369+00:00"
  },
  {
    "id": "208",
    "from_email": "Brightflag <invoices@brightflag.com>",
    "to_email": "Suphattra",
    "subject": "Action Needed - Email Verification - Brightflag",
    "received_at": "2026-03-24T07:12:37+00:00",
    "otp_code": "178439",
    "virtru_link": null,
    "valid_until": null,
    "expiry_str": "15 minutes",
    "expiry_minutes": 15,
    "expires_at": "2026-03-24T07:27:37+00:00",
    "system_name": "Brightflag",
    "system_url": "https://brightflag.com",
    "color": "#059669",
    "parsed_at": "2026-04-10T07:34:53.093504+00:00"
  },
  {
    "id": "207",
    "from_email": "donotreply <DoNotReply@qualcomm.com>",
    "to_email": "prabjote@dsb.co.th",
    "subject": "One-time verification code",
    "received_at": "2026-03-24T06:57:04+00:00",
    "otp_code": "170191",
    "virtru_link": null,
    "valid_until": null,
    "expiry_str": "ไม่ระบุ",
    "expiry_minutes": null,
    "expires_at": null,
    "system_name": "Qualcomm (Okta)",
    "system_url": "https://account.qualcomm.com",
    "color": "#3253DC",
    "parsed_at": "2026-04-10T07:34:53.085964+00:00"
  },
  {
    "id": "206",
    "from_email": "Brightflag <invoices@brightflag.com>",
    "to_email": "otp-code@dsb.co.th",
    "subject": "Action Needed - Email Verification - Brightflag",
    "received_at": "2026-03-24T05:56:35+00:00",
    "otp_code": "999999",
    "virtru_link": null,
    "valid_until": null,
    "expiry_str": "15 minutes",
    "expiry_minutes": 15,
    "expires_at": "2026-03-24T06:11:35+00:00",
    "system_name": "Brightflag",
    "system_url": "https://brightflag.com",
    "color": "#059669",
    "parsed_at": "2026-04-10T07:34:53.078732+00:00"
  },
  {
    "id": "205",
    "from_email": "Mitratech Support <collaborati-noreply@mitratech.com>",
    "to_email": "Rutorn",
    "subject": "Collaborati - Verification Code",
    "received_at": "2026-03-24T03:50:14+00:00",
    "otp_code": "997164",
    "virtru_link": null,
    "valid_until": null,
    "expiry_str": "10 minutes",
    "expiry_minutes": 10,
    "expires_at": "2026-03-24T04:00:14+00:00",
    "system_name": "Collaborati (Mitratech)",
    "system_url": "https://www.collaborati.net",
    "color": "#002453",
    "parsed_at": "2026-04-10T07:34:53.071186+00:00"
  },
  {
    "id": "204",
    "from_email": "west.onepass@thomsonreuters.com",
    "to_email": "Rutorn",
    "subject": "OnePass Security Code",
    "received_at": "2026-03-23T12:27:49+00:00",
    "otp_code": "447775",
    "virtru_link": null,
    "valid_until": null,
    "expiry_str": "15 minutes",
    "expiry_minutes": 15,
    "expires_at": "2026-03-23T12:42:49+00:00",
    "system_name": "OnePass (Thomson Reuters)",
    "system_url": "https://onepass.thomsonreuters.com",
    "color": "#DC2626",
    "parsed_at": "2026-04-10T07:34:53.063585+00:00"
  },
  {
    "id": "203",
    "from_email": "west.onepass@thomsonreuters.com",
    "to_email": "Rutorn",
    "subject": "OnePass Security Code",
    "received_at": "2026-03-23T09:08:01+00:00",
    "otp_code": "578185",
    "virtru_link": null,
    "valid_until": null,
    "expiry_str": "15 minutes",
    "expiry_minutes": 15,
    "expires_at": "2026-03-23T09:23:01+00:00",
    "system_name": "OnePass (Thomson Reuters)",
    "system_url": "https://onepass.thomsonreuters.com",
    "color": "#DC2626",
    "parsed_at": "2026-04-10T07:34:53.057251+00:00"
  },
  {
    "id": "202",
    "from_email": "donotreply <DoNotReply@qualcomm.com>",
    "to_email": "prabjote@dsb.co.th",
    "subject": "One-time verification code",
    "received_at": "2026-03-23T07:00:35+00:00",
    "otp_code": "443753",
    "virtru_link": null,
    "valid_until": null,
    "expiry_str": "ไม่ระบุ",
    "expiry_minutes": null,
    "expires_at": null,
    "system_name": "Qualcomm (Okta)",
    "system_url": "https://account.qualcomm.com",
    "color": "#3253DC",
    "parsed_at": "2026-04-10T07:34:53.050713+00:00"
  },
  {
    "id": "201",
    "from_email": "hqimtsc.noreply@nestle.com",
    "to_email": "Rutorn",
    "subject": " OTP Verification Nestlé Invoice Management Tool",
    "received_at": "2026-03-23T06:55:41+00:00",
    "otp_code": "749310",
    "virtru_link": null,
    "valid_until": null,
    "expiry_str": "ไม่ระบุ",
    "expiry_minutes": null,
    "expires_at": null,
    "system_name": "Nestlé Invoice Management",
    "system_url": "https://nestle.com",
    "color": "#c8102e",
    "parsed_at": "2026-04-10T07:34:53.043956+00:00"
  },
  {
    "id": "200",
    "from_email": "hqimtsc.noreply@nestle.com",
    "to_email": "Rutorn",
    "subject": " OTP Verification Nestlé Invoice Management Tool",
    "received_at": "2026-03-23T06:41:52+00:00",
    "otp_code": "943239",
    "virtru_link": null,
    "valid_until": null,
    "expiry_str": "ไม่ระบุ",
    "expiry_minutes": null,
    "expires_at": null,
    "system_name": "Nestlé Invoice Management",
    "system_url": "https://nestle.com",
    "color": "#c8102e",
    "parsed_at": "2026-04-10T07:34:53.035871+00:00"
  },
  {
    "id": "199",
    "from_email": "hqimtsc.noreply@nestle.com",
    "to_email": "Rutorn",
    "subject": " OTP Verification Nestlé Invoice Management Tool",
    "received_at": "2026-03-23T00:19:58+00:00",
    "otp_code": "630779",
    "virtru_link": null,
    "valid_until": null,
    "expiry_str": "ไม่ระบุ",
    "expiry_minutes": null,
    "expires_at": null,
    "system_name": "Nestlé Invoice Management",
    "system_url": "https://nestle.com",
    "color": "#c8102e",
    "parsed_at": "2026-04-10T07:34:53.029523+00:00"
  },
  {
    "id": "198",
    "from_email": "donotreply <DoNotReply@qualcomm.com>",
    "to_email": "prabjote@dsb.co.th",
    "subject": "One-time verification code",
    "received_at": "2026-03-22T02:58:42+00:00",
    "otp_code": "456868",
    "virtru_link": null,
    "valid_until": null,
    "expiry_str": "ไม่ระบุ",
    "expiry_minutes": null,
    "expires_at": null,
    "system_name": "Qualcomm (Okta)",
    "system_url": "https://account.qualcomm.com",
    "color": "#3253DC",
    "parsed_at": "2026-04-10T07:34:53.023034+00:00"
  },
  {
    "id": "196",
    "from_email": "hqimtsc.noreply@nestle.com",
    "to_email": "Rutorn",
    "subject": " OTP Verification Nestlé Invoice Management Tool",
    "received_at": "2026-03-21T05:02:41+00:00",
    "otp_code": "177144",
    "virtru_link": null,
    "valid_until": null,
    "expiry_str": "ไม่ระบุ",
    "expiry_minutes": null,
    "expires_at": null,
    "system_name": "Nestlé Invoice Management",
    "system_url": "https://nestle.com",
    "color": "#c8102e",
    "parsed_at": "2026-04-10T07:34:53.007734+00:00"
  },
  {
    "id": "195",
    "from_email": "hqimtsc.noreply@nestle.com",
    "to_email": "Rutorn",
    "subject": " OTP Verification Nestlé Invoice Management Tool",
    "received_at": "2026-03-21T04:17:56+00:00",
    "otp_code": "456072",
    "virtru_link": null,
    "valid_until": null,
    "expiry_str": "ไม่ระบุ",
    "expiry_minutes": null,
    "expires_at": null,
    "system_name": "Nestlé Invoice Management",
    "system_url": "https://nestle.com",
    "color": "#c8102e",
    "parsed_at": "2026-04-10T07:34:53.002308+00:00"
  },
  {
    "id": "194",
    "from_email": "Billingpoint <no-reply@onit.com>",
    "to_email": "Suphattra",
    "subject": "Billing Point secure login code",
    "received_at": "2026-03-20T08:34:06+00:00",
    "otp_code": "440618",
    "virtru_link": null,
    "valid_until": null,
    "expiry_str": "ไม่ระบุ",
    "expiry_minutes": null,
    "expires_at": null,
    "system_name": "Billing Point (Onit)",
    "system_url": "https://billingpoint.onit.com",
    "color": "#7c3aed",
    "parsed_at": "2026-04-10T07:34:52.995911+00:00"
  },
  {
    "id": "193",
    "from_email": "CounselLink <no-reply@lexisnexis.com>",
    "to_email": "Rutorn",
    "subject": "CounselLink Multi-factor Authentication Verification Code",
    "received_at": "2026-03-20T08:13:05+00:00",
    "otp_code": "537331",
    "virtru_link": null,
    "valid_until": null,
    "expiry_str": "10 minutes",
    "expiry_minutes": 10,
    "expires_at": "2026-03-20T08:23:05+00:00",
    "system_name": "CounselLink (LexisNexis)",
    "system_url": "https://counsellink.com",
    "color": "#d61f1f",
    "parsed_at": "2026-04-10T07:34:52.988775+00:00"
  },
  {
    "id": "192",
    "from_email": "Billingpoint <no-reply@onit.com>",
    "to_email": "Suphattra",
    "subject": "Billing Point secure login code",
    "received_at": "2026-03-20T07:49:07+00:00",
    "otp_code": "261595",
    "virtru_link": null,
    "valid_until": null,
    "expiry_str": "ไม่ระบุ",
    "expiry_minutes": null,
    "expires_at": null,
    "system_name": "Billing Point (Onit)",
    "system_url": "https://billingpoint.onit.com",
    "color": "#7c3aed",
    "parsed_at": "2026-04-10T07:34:52.981409+00:00"
  },
  {
    "id": "191",
    "from_email": "donotreply <DoNotReply@qualcomm.com>",
    "to_email": "prabjote@dsb.co.th",
    "subject": "One-time verification code",
    "received_at": "2026-03-20T06:27:59+00:00",
    "otp_code": "445797",
    "virtru_link": null,
    "valid_until": null,
    "expiry_str": "ไม่ระบุ",
    "expiry_minutes": null,
    "expires_at": null,
    "system_name": "Qualcomm (Okta)",
    "system_url": "https://account.qualcomm.com",
    "color": "#3253DC",
    "parsed_at": "2026-04-10T07:34:52.974250+00:00"
  },
  {
    "id": "190",
    "from_email": "CounselLink <no-reply@lexisnexis.com>",
    "to_email": "Rutorn",
    "subject": "CounselLink Multi-factor Authentication Verification Code",
    "received_at": "2026-03-20T03:02:04+00:00",
    "otp_code": "448222",
    "virtru_link": null,
    "valid_until": null,
    "expiry_str": "10 minutes",
    "expiry_minutes": 10,
    "expires_at": "2026-03-20T03:12:04+00:00",
    "system_name": "CounselLink (LexisNexis)",
    "system_url": "https://counsellink.com",
    "color": "#d61f1f",
    "parsed_at": "2026-04-10T07:34:52.967069+00:00"
  },
  {
    "id": "189",
    "from_email": "Mitratech Support <collaborati-noreply@mitratech.com>",
    "to_email": "Rutorn",
    "subject": "Collaborati - Verification Code",
    "received_at": "2026-03-20T02:58:07+00:00",
    "otp_code": "403520",
    "virtru_link": null,
    "valid_until": null,
    "expiry_str": "10 minutes",
    "expiry_minutes": 10,
    "expires_at": "2026-03-20T03:08:07+00:00",
    "system_name": "Collaborati (Mitratech)",
    "system_url": "https://www.collaborati.net",
    "color": "#002453",
    "parsed_at": "2026-04-10T07:34:52.959544+00:00"
  },
  {
    "id": "188",
    "from_email": "CounselLink <no-reply@lexisnexis.com>",
    "to_email": "Rutorn",
    "subject": "CounselLink Multi-factor Authentication Verification Code",
    "received_at": "2026-03-20T02:38:54+00:00",
    "otp_code": "629681",
    "virtru_link": null,
    "valid_until": null,
    "expiry_str": "10 minutes",
    "expiry_minutes": 10,
    "expires_at": "2026-03-20T02:48:54+00:00",
    "system_name": "CounselLink (LexisNexis)",
    "system_url": "https://counsellink.com",
    "color": "#d61f1f",
    "parsed_at": "2026-04-10T07:34:52.952726+00:00"
  },
  {
    "id": "187",
    "from_email": "west.onepass@thomsonreuters.com",
    "to_email": "Rutorn",
    "subject": "OnePass Security Code",
    "received_at": "2026-03-20T01:57:16+00:00",
    "otp_code": "404351",
    "virtru_link": null,
    "valid_until": null,
    "expiry_str": "15 minutes",
    "expiry_minutes": 15,
    "expires_at": "2026-03-20T02:12:16+00:00",
    "system_name": "OnePass (Thomson Reuters)",
    "system_url": "https://onepass.thomsonreuters.com",
    "color": "#DC2626",
    "parsed_at": "2026-04-10T07:34:52.945675+00:00"
  },
  {
    "id": "186",
    "from_email": "Mitratech Support <collaborati-noreply@mitratech.com>",
    "to_email": "Rutorn",
    "subject": "Collaborati - Verification Code",
    "received_at": "2026-03-20T01:20:02+00:00",
    "otp_code": "594426",
    "virtru_link": null,
    "valid_until": null,
    "expiry_str": "10 minutes",
    "expiry_minutes": 10,
    "expires_at": "2026-03-20T01:30:02+00:00",
    "system_name": "Collaborati (Mitratech)",
    "system_url": "https://www.collaborati.net",
    "color": "#002453",
    "parsed_at": "2026-04-10T07:34:52.939295+00:00"
  },
  {
    "id": "185",
    "from_email": "Mitratech Support <collaborati-noreply@mitratech.com>",
    "to_email": "Rutorn",
    "subject": "Collaborati - Verification Code",
    "received_at": "2026-03-20T00:52:50+00:00",
    "otp_code": "442740",
    "virtru_link": null,
    "valid_until": null,
    "expiry_str": "10 minutes",
    "expiry_minutes": 10,
    "expires_at": "2026-03-20T01:02:50+00:00",
    "system_name": "Collaborati (Mitratech)",
    "system_url": "https://www.collaborati.net",
    "color": "#002453",
    "parsed_at": "2026-04-10T07:34:52.932478+00:00"
  },
  {
    "id": "184",
    "from_email": "CounselLink <no-reply@lexisnexis.com>",
    "to_email": "Rutorn",
    "subject": "CounselLink Multi-factor Authentication Verification Code",
    "received_at": "2026-03-19T07:54:24+00:00",
    "otp_code": "158253",
    "virtru_link": null,
    "valid_until": null,
    "expiry_str": "10 minutes",
    "expiry_minutes": 10,
    "expires_at": "2026-03-19T08:04:24+00:00",
    "system_name": "CounselLink (LexisNexis)",
    "system_url": "https://counsellink.com",
    "color": "#d61f1f",
    "parsed_at": "2026-04-10T07:34:52.924758+00:00"
  },
  {
    "id": "183",
    "from_email": "donotreply <DoNotReply@qualcomm.com>",
    "to_email": "prabjote@dsb.co.th",
    "subject": "One-time verification code",
    "received_at": "2026-03-19T07:49:59+00:00",
    "otp_code": "977590",
    "virtru_link": null,
    "valid_until": null,
    "expiry_str": "ไม่ระบุ",
    "expiry_minutes": null,
    "expires_at": null,
    "system_name": "Qualcomm (Okta)",
    "system_url": "https://account.qualcomm.com",
    "color": "#3253DC",
    "parsed_at": "2026-04-10T07:34:52.917779+00:00"
  },
  {
    "id": "182",
    "from_email": "donotreply <DoNotReply@qualcomm.com>",
    "to_email": "prabjote@dsb.co.th",
    "subject": "One-time verification code",
    "received_at": "2026-03-19T04:53:32+00:00",
    "otp_code": "855864",
    "virtru_link": null,
    "valid_until": null,
    "expiry_str": "ไม่ระบุ",
    "expiry_minutes": null,
    "expires_at": null,
    "system_name": "Qualcomm (Okta)",
    "system_url": "https://account.qualcomm.com",
    "color": "#3253DC",
    "parsed_at": "2026-04-10T07:34:52.910606+00:00"
  },
  {
    "id": "181",
    "from_email": "Billingpoint <no-reply@onit.com>",
    "to_email": "Suphattra",
    "subject": "Billing Point secure login code",
    "received_at": "2026-03-18T09:59:37+00:00",
    "otp_code": "839230",
    "virtru_link": null,
    "valid_until": null,
    "expiry_str": "ไม่ระบุ",
    "expiry_minutes": null,
    "expires_at": null,
    "system_name": "Billing Point (Onit)",
    "system_url": "https://billingpoint.onit.com",
    "color": "#7c3aed",
    "parsed_at": "2026-04-10T07:34:52.903440+00:00"
  },
  {
    "id": "180",
    "from_email": "hqimtsc.noreply@nestle.com",
    "to_email": "Rutorn",
    "subject": " OTP Verification Nestlé Invoice Management Tool",
    "received_at": "2026-03-18T06:41:22+00:00",
    "otp_code": "770691",
    "virtru_link": null,
    "valid_until": null,
    "expiry_str": "ไม่ระบุ",
    "expiry_minutes": null,
    "expires_at": null,
    "system_name": "Nestlé Invoice Management",
    "system_url": "https://nestle.com",
    "color": "#c8102e",
    "parsed_at": "2026-04-10T07:34:52.896622+00:00"
  },
  {
    "id": "179",
    "from_email": "donotreply <DoNotReply@qualcomm.com>",
    "to_email": "prabjote@dsb.co.th",
    "subject": "One-time verification code",
    "received_at": "2026-03-18T03:21:33+00:00",
    "otp_code": "381952",
    "virtru_link": null,
    "valid_until": null,
    "expiry_str": "ไม่ระบุ",
    "expiry_minutes": null,
    "expires_at": null,
    "system_name": "Qualcomm (Okta)",
    "system_url": "https://account.qualcomm.com",
    "color": "#3253DC",
    "parsed_at": "2026-04-10T07:34:52.890037+00:00"
  },
  {
    "id": "178",
    "from_email": "donotreply <DoNotReply@qualcomm.com>",
    "to_email": "prabjote@dsb.co.th",
    "subject": "One-time verification code",
    "received_at": "2026-03-18T00:02:06+00:00",
    "otp_code": "905095",
    "virtru_link": null,
    "valid_until": null,
    "expiry_str": "ไม่ระบุ",
    "expiry_minutes": null,
    "expires_at": null,
    "system_name": "Qualcomm (Okta)",
    "system_url": "https://account.qualcomm.com",
    "color": "#3253DC",
    "parsed_at": "2026-04-10T07:34:52.882595+00:00"
  },
  {
    "id": "177",
    "from_email": "Billingpoint <no-reply@onit.com>",
    "to_email": "Suphattra",
    "subject": "Billing Point secure login code",
    "received_at": "2026-03-17T08:19:29+00:00",
    "otp_code": "664506",
    "virtru_link": null,
    "valid_until": null,
    "expiry_str": "ไม่ระบุ",
    "expiry_minutes": null,
    "expires_at": null,
    "system_name": "Billing Point (Onit)",
    "system_url": "https://billingpoint.onit.com",
    "color": "#7c3aed",
    "parsed_at": "2026-04-10T07:34:52.875366+00:00"
  },
  {
    "id": "176",
    "from_email": "Billingpoint <no-reply@onit.com>",
    "to_email": "Suphattra",
    "subject": "Billing Point secure login code",
    "received_at": "2026-03-17T07:10:02+00:00",
    "otp_code": "711646",
    "virtru_link": null,
    "valid_until": null,
    "expiry_str": "ไม่ระบุ",
    "expiry_minutes": null,
    "expires_at": null,
    "system_name": "Billing Point (Onit)",
    "system_url": "https://billingpoint.onit.com",
    "color": "#7c3aed",
    "parsed_at": "2026-04-10T07:34:52.868004+00:00"
  },
  {
    "id": "175",
    "from_email": "donotreply <DoNotReply@qualcomm.com>",
    "to_email": "prabjote@dsb.co.th",
    "subject": "One-time verification code",
    "received_at": "2026-03-17T03:32:06+00:00",
    "otp_code": "015857",
    "virtru_link": null,
    "valid_until": null,
    "expiry_str": "ไม่ระบุ",
    "expiry_minutes": null,
    "expires_at": null,
    "system_name": "Qualcomm (Okta)",
    "system_url": "https://account.qualcomm.com",
    "color": "#3253DC",
    "parsed_at": "2026-04-10T07:34:52.861192+00:00"
  },
  {
    "id": "174",
    "from_email": "donotreply <DoNotReply@qualcomm.com>",
    "to_email": "prabjote@dsb.co.th",
    "subject": "One-time verification code",
    "received_at": "2026-03-17T03:18:38+00:00",
    "otp_code": "154794",
    "virtru_link": null,
    "valid_until": null,
    "expiry_str": "ไม่ระบุ",
    "expiry_minutes": null,
    "expires_at": null,
    "system_name": "Qualcomm (Okta)",
    "system_url": "https://account.qualcomm.com",
    "color": "#3253DC",
    "parsed_at": "2026-04-10T07:34:52.853930+00:00"
  },
  {
    "id": "173",
    "from_email": "hqimtsc.noreply@nestle.com",
    "to_email": "Rutorn",
    "subject": " OTP Verification Nestlé Invoice Management Tool",
    "received_at": "2026-03-17T02:57:24+00:00",
    "otp_code": "419295",
    "virtru_link": null,
    "valid_until": null,
    "expiry_str": "ไม่ระบุ",
    "expiry_minutes": null,
    "expires_at": null,
    "system_name": "Nestlé Invoice Management",
    "system_url": "https://nestle.com",
    "color": "#c8102e",
    "parsed_at": "2026-04-10T07:34:52.846730+00:00"
  },
  {
    "id": "172",
    "from_email": "CounselLink <no-reply@lexisnexis.com>",
    "to_email": "Rutorn",
    "subject": "CounselLink Multi-factor Authentication Verification Code",
    "received_at": "2026-03-17T02:11:07+00:00",
    "otp_code": "908779",
    "virtru_link": null,
    "valid_until": null,
    "expiry_str": "10 minutes",
    "expiry_minutes": 10,
    "expires_at": "2026-03-17T02:21:07+00:00",
    "system_name": "CounselLink (LexisNexis)",
    "system_url": "https://counsellink.com",
    "color": "#d61f1f",
    "parsed_at": "2026-04-10T07:34:52.840807+00:00"
  },
  {
    "id": "171",
    "from_email": "CounselLink <no-reply@lexisnexis.com>",
    "to_email": "Rutorn",
    "subject": "CounselLink Multi-factor Authentication Verification Code",
    "received_at": "2026-03-16T09:24:57+00:00",
    "otp_code": "629233",
    "virtru_link": null,
    "valid_until": null,
    "expiry_str": "10 minutes",
    "expiry_minutes": 10,
    "expires_at": "2026-03-16T09:34:57+00:00",
    "system_name": "CounselLink (LexisNexis)",
    "system_url": "https://counsellink.com",
    "color": "#d61f1f",
    "parsed_at": "2026-04-10T07:34:52.833837+00:00"
  },
  {
    "id": "170",
    "from_email": "donotreply <DoNotReply@qualcomm.com>",
    "to_email": "prabjote@dsb.co.th",
    "subject": "One-time verification code",
    "received_at": "2026-03-16T07:47:32+00:00",
    "otp_code": "157490",
    "virtru_link": null,
    "valid_until": null,
    "expiry_str": "ไม่ระบุ",
    "expiry_minutes": null,
    "expires_at": null,
    "system_name": "Qualcomm (Okta)",
    "system_url": "https://account.qualcomm.com",
    "color": "#3253DC",
    "parsed_at": "2026-04-10T07:34:52.826409+00:00"
  },
  {
    "id": "169",
    "from_email": "donotreply <DoNotReply@qualcomm.com>",
    "to_email": "prabjote@dsb.co.th",
    "subject": "One-time verification code",
    "received_at": "2026-03-16T07:45:34+00:00",
    "otp_code": "731408",
    "virtru_link": null,
    "valid_until": null,
    "expiry_str": "ไม่ระบุ",
    "expiry_minutes": null,
    "expires_at": null,
    "system_name": "Qualcomm (Okta)",
    "system_url": "https://account.qualcomm.com",
    "color": "#3253DC",
    "parsed_at": "2026-04-10T07:34:52.820026+00:00"
  }
]